{
    "data": {
        "year": "2021",
        "metroareas": [
            {
                "metro_name": "Blacksburg-Christiansburg-Radford, VA HUD Metro FMR Area",
                "code": "METRO13980M13980",
                "Efficiency": 795,
                "One-Bedroom": 858,
                "Two-Bedroom": 978,
                "Three-Bedroom": 1400,
                "Four-Bedroom": 1693,
                "FMR Percentile": 40,
                "statename": "Virginia",
                "statecode": "VA",
                "smallarea_status": "0"
            },
            {
                "metro_name": "Buckingham County, VA HUD Metro FMR Area",
                "code": "METRO16820N51029",
                "Efficiency": 564,
                "One-Bedroom": 652,
                "Two-Bedroom": 743,
                "Three-Bedroom": 1007,
                "Four-Bedroom": 1140,
                "FMR Percentile": 40,
                "statename": "Virginia",
                "statecode": "VA",
                "smallarea_status": "0"
            },
            {
                "metro_name": "Charlottesville, VA HUD Metro FMR Area",
                "code": "METRO16820M16820",
                "Efficiency": 949,
                "One-Bedroom": 1077,
                "Two-Bedroom": 1266,
                "Three-Bedroom": 1575,
                "Four-Bedroom": 1965,
                "FMR Percentile": 40,
                "statename": "Virginia",
                "statecode": "VA",
                "smallarea_status": "0"
            },
            {
                "metro_name": "Culpeper County, VA HUD Metro FMR Area",
                "code": "METRO47900N51047",
                "Efficiency": 788,
                "One-Bedroom": 794,
                "Two-Bedroom": 1046,
                "Three-Bedroom": 1439,
                "Four-Bedroom": 1811,
                "FMR Percentile": 40,
                "statename": "Virginia",
                "statecode": "VA",
                "smallarea_status": "0"
            },
            {
                "metro_name": "Floyd County, VA HUD Metro FMR Area",
                "code": "METRO13980N51063",
                "Efficiency": 601,
                "One-Bedroom": 615,
                "Two-Bedroom": 701,
                "Three-Bedroom": 1003,
                "Four-Bedroom": 1214,
                "FMR Percentile": 40,
                "statename": "Virginia",
                "statecode": "VA",
                "smallarea_status": "0"
            },
            {
                "metro_name": "Franklin County, VA HUD Metro FMR Area",
                "code": "METRO40220N51067",
                "Efficiency": 575,
                "One-Bedroom": 618,
                "Two-Bedroom": 815,
                "Three-Bedroom": 1014,
                "Four-Bedroom": 1127,
                "FMR Percentile": 40,
                "statename": "Virginia",
                "statecode": "VA",
                "smallarea_status": "0"
            },
            {
                "metro_name": "Giles County, VA HUD Metro FMR Area",
                "code": "METRO13980N51071",
                "Efficiency": 504,
                "One-Bedroom": 655,
                "Two-Bedroom": 747,
                "Three-Bedroom": 982,
                "Four-Bedroom": 1099,
                "FMR Percentile": 40,
                "statename": "Virginia",
                "statecode": "VA",
                "smallarea_status": "0"
            },
            {
                "metro_name": "Harrisonburg, VA MSA",
                "code": "METRO25500M25500",
                "Efficiency": 699,
                "One-Bedroom": 703,
                "Two-Bedroom": 927,
                "Three-Bedroom": 1207,
                "Four-Bedroom": 1605,
                "FMR Percentile": 40,
                "statename": "Virginia",
                "statecode": "VA",
                "smallarea_status": "0"
            },
            {
                "metro_name": "Kingsport-Bristol-Bristol, TN-VA MSA",
                "code": "METRO28700M28700",
                "Efficiency": 513,
                "One-Bedroom": 533,
                "Two-Bedroom": 701,
                "Three-Bedroom": 916,
                "Four-Bedroom": 1008,
                "FMR Percentile": 40,
                "statename": "Virginia",
                "statecode": "VA",
                "smallarea_status": "0"
            },
            {
                "metro_name": "Lynchburg, VA MSA",
                "code": "METRO31340M31340",
                "Efficiency": 633,
                "One-Bedroom": 660,
                "Two-Bedroom": 784,
                "Three-Bedroom": 1053,
                "Four-Bedroom": 1241,
                "FMR Percentile": 40,
                "statename": "Virginia",
                "statecode": "VA",
                "smallarea_status": "0"
            },
            {
                "metro_name": "Pulaski County, VA HUD Metro FMR Area",
                "code": "METRO13980N51155",
                "Efficiency": 618,
                "One-Bedroom": 631,
                "Two-Bedroom": 721,
                "Three-Bedroom": 1005,
                "Four-Bedroom": 1191,
                "FMR Percentile": 40,
                "statename": "Virginia",
                "statecode": "VA",
                "smallarea_status": "0"
            },
            {
                "metro_name": "Rappahannock County, VA HUD Metro FMR Area",
                "code": "METRO47900N51157",
                "Efficiency": 921,
                "One-Bedroom": 942,
                "Two-Bedroom": 1074,
                "Three-Bedroom": 1433,
                "Four-Bedroom": 1664,
                "FMR Percentile": 40,
                "statename": "Virginia",
                "statecode": "VA",
                "smallarea_status": "0"
            },
            {
                "metro_name": "Richmond, VA MSA",
                "code": "METRO40060M40060",
                "Efficiency": 993,
                "One-Bedroom": 1020,
                "Two-Bedroom": 1163,
                "Three-Bedroom": 1538,
                "Four-Bedroom": 1840,
                "FMR Percentile": 40,
                "statename": "Virginia",
                "statecode": "VA",
                "smallarea_status": "0"
            },
            {
                "metro_name": "Roanoke, VA HUD Metro FMR Area",
                "code": "METRO40220M40220",
                "Efficiency": 641,
                "One-Bedroom": 743,
                "Two-Bedroom": 941,
                "Three-Bedroom": 1268,
                "Four-Bedroom": 1387,
                "FMR Percentile": 40,
                "statename": "Virginia",
                "statecode": "VA",
                "smallarea_status": "0"
            },
            {
                "metro_name": "Staunton-Waynesboro, VA MSA",
                "code": "METRO44420M44420",
                "Efficiency": 690,
                "One-Bedroom": 695,
                "Two-Bedroom": 910,
                "Three-Bedroom": 1239,
                "Four-Bedroom": 1416,
                "FMR Percentile": 40,
                "statename": "Virginia",
                "statecode": "VA",
                "smallarea_status": "0"
            },
            {
                "metro_name": "Virginia Beach-Norfolk-Newport News, VA-NC HUD Metro FMR Area",
                "code": "METRO47260M47260",
                "Efficiency": 960,
                "One-Bedroom": 972,
                "Two-Bedroom": 1147,
                "Three-Bedroom": 1618,
                "Four-Bedroom": 1986,
                "FMR Percentile": 40,
                "statename": "Virginia",
                "statecode": "VA",
                "smallarea_status": "0"
            },
            {
                "metro_name": "Warren County, VA HUD Metro FMR Area",
                "code": "METRO47900MM8820",
                "Efficiency": 676,
                "One-Bedroom": 777,
                "Two-Bedroom": 1024,
                "Three-Bedroom": 1376,
                "Four-Bedroom": 1773,
                "FMR Percentile": 40,
                "statename": "Virginia",
                "statecode": "VA",
                "smallarea_status": "0"
            },
            {
                "metro_name": "Washington-Arlington-Alexandria, DC-VA-MD HUD Metro FMR Area",
                "code": "METRO47900M47900",
                "Efficiency": 1513,
                "One-Bedroom": 1548,
                "Two-Bedroom": 1765,
                "Three-Bedroom": 2263,
                "Four-Bedroom": 2742,
                "FMR Percentile": 40,
                "statename": "Virginia",
                "statecode": "VA",
                "smallarea_status": "1"
            },
            {
                "metro_name": "Winchester, VA-WV MSA",
                "code": "METRO49020M49020",
                "Efficiency": 814,
                "One-Bedroom": 819,
                "Two-Bedroom": 1064,
                "Three-Bedroom": 1399,
                "Four-Bedroom": 1814,
                "FMR Percentile": 40,
                "statename": "Virginia",
                "statecode": "VA",
                "smallarea_status": "0"
            }
        ],
        "counties": [
            {
                "town_name": null,
                "county_name": "Accomack County",
                "metro_name": "Accomack County, VA",
                "fips_code": "5100199999",
                "Efficiency": 481,
                "One-Bedroom": 602,
                "Two-Bedroom": 713,
                "Three-Bedroom": 947,
                "Four-Bedroom": 967,
                "FMR Percentile": 40,
                "statename": "Virginia",
                "statecode": "VA",
                "smallarea_status": "0"
            },
            {
                "town_name": null,
                "county_name": "Albemarle County",
                "metro_name": "Charlottesville, VA HUD Metro FMR Area",
                "fips_code": "5100399999",
                "Efficiency": 949,
                "One-Bedroom": 1077,
                "Two-Bedroom": 1266,
                "Three-Bedroom": 1575,
                "Four-Bedroom": 1965,
                "FMR Percentile": 40,
                "statename": "Virginia",
                "statecode": "VA",
                "smallarea_status": "0"
            },
            {
                "town_name": null,
                "county_name": "Alexandria city",
                "metro_name": "Washington-Arlington-Alexandria, DC-VA-MD HUD Metro FMR Area",
                "fips_code": "5151099999",
                "Efficiency": 1513,
                "One-Bedroom": 1548,
                "Two-Bedroom": 1765,
                "Three-Bedroom": 2263,
                "Four-Bedroom": 2742,
                "FMR Percentile": 40,
                "statename": "Virginia",
                "statecode": "VA",
                "smallarea_status": "1"
            },
            {
                "town_name": null,
                "county_name": "Alleghany County",
                "metro_name": "Alleghany County-Clifton Forge city-Covington city, VA HUD Nonmetro FMR Area",
                "fips_code": "5100599999",
                "Efficiency": 495,
                "One-Bedroom": 558,
                "Two-Bedroom": 735,
                "Three-Bedroom": 958,
                "Four-Bedroom": 1142,
                "FMR Percentile": 40,
                "statename": "Virginia",
                "statecode": "VA",
                "smallarea_status": "0"
            },
            {
                "town_name": null,
                "county_name": "Amelia County",
                "metro_name": "Richmond, VA MSA",
                "fips_code": "5100799999",
                "Efficiency": 993,
                "One-Bedroom": 1020,
                "Two-Bedroom": 1163,
                "Three-Bedroom": 1538,
                "Four-Bedroom": 1840,
                "FMR Percentile": 40,
                "statename": "Virginia",
                "statecode": "VA",
                "smallarea_status": "0"
            },
            {
                "town_name": null,
                "county_name": "Amherst County",
                "metro_name": "Lynchburg, VA MSA",
                "fips_code": "5100999999",
                "Efficiency": 633,
                "One-Bedroom": 660,
                "Two-Bedroom": 784,
                "Three-Bedroom": 1053,
                "Four-Bedroom": 1241,
                "FMR Percentile": 40,
                "statename": "Virginia",
                "statecode": "VA",
                "smallarea_status": "0"
            },
            {
                "town_name": null,
                "county_name": "Appomattox County",
                "metro_name": "Lynchburg, VA MSA",
                "fips_code": "5101199999",
                "Efficiency": 633,
                "One-Bedroom": 660,
                "Two-Bedroom": 784,
                "Three-Bedroom": 1053,
                "Four-Bedroom": 1241,
                "FMR Percentile": 40,
                "statename": "Virginia",
                "statecode": "VA",
                "smallarea_status": "0"
            },
            {
                "town_name": null,
                "county_name": "Arlington County",
                "metro_name": "Washington-Arlington-Alexandria, DC-VA-MD HUD Metro FMR Area",
                "fips_code": "5101399999",
                "Efficiency": 1513,
                "One-Bedroom": 1548,
                "Two-Bedroom": 1765,
                "Three-Bedroom": 2263,
                "Four-Bedroom": 2742,
                "FMR Percentile": 40,
                "statename": "Virginia",
                "statecode": "VA",
                "smallarea_status": "1"
            },
            {
                "town_name": null,
                "county_name": "Augusta County",
                "metro_name": "Staunton-Waynesboro, VA MSA",
                "fips_code": "5101599999",
                "Efficiency": 690,
                "One-Bedroom": 695,
                "Two-Bedroom": 910,
                "Three-Bedroom": 1239,
                "Four-Bedroom": 1416,
                "FMR Percentile": 40,
                "statename": "Virginia",
                "statecode": "VA",
                "smallarea_status": "0"
            },
            {
                "town_name": null,
                "county_name": "Bath County",
                "metro_name": "Bath County, VA",
                "fips_code": "5101799999",
                "Efficiency": 475,
                "One-Bedroom": 559,
                "Two-Bedroom": 705,
                "Three-Bedroom": 937,
                "Four-Bedroom": 1041,
                "FMR Percentile": 40,
                "statename": "Virginia",
                "statecode": "VA",
                "smallarea_status": "0"
            },
            {
                "town_name": null,
                "county_name": "Bedford County",
                "metro_name": "Lynchburg, VA MSA",
                "fips_code": "5101999999",
                "Efficiency": 633,
                "One-Bedroom": 660,
                "Two-Bedroom": 784,
                "Three-Bedroom": 1053,
                "Four-Bedroom": 1241,
                "FMR Percentile": 40,
                "statename": "Virginia",
                "statecode": "VA",
                "smallarea_status": "0"
            },
            {
                "town_name": null,
                "county_name": "Bland County",
                "metro_name": "Bland County, VA",
                "fips_code": "5102199999",
                "Efficiency": 472,
                "One-Bedroom": 556,
                "Two-Bedroom": 701,
                "Three-Bedroom": 950,
                "Four-Bedroom": 1035,
                "FMR Percentile": 40,
                "statename": "Virginia",
                "statecode": "VA",
                "smallarea_status": "0"
            },
            {
                "town_name": null,
                "county_name": "Botetourt County",
                "metro_name": "Roanoke, VA HUD Metro FMR Area",
                "fips_code": "5102399999",
                "Efficiency": 641,
                "One-Bedroom": 743,
                "Two-Bedroom": 941,
                "Three-Bedroom": 1268,
                "Four-Bedroom": 1387,
                "FMR Percentile": 40,
                "statename": "Virginia",
                "statecode": "VA",
                "smallarea_status": "0"
            },
            {
                "town_name": null,
                "county_name": "Bristol city",
                "metro_name": "Kingsport-Bristol-Bristol, TN-VA MSA",
                "fips_code": "5152099999",
                "Efficiency": 513,
                "One-Bedroom": 533,
                "Two-Bedroom": 701,
                "Three-Bedroom": 916,
                "Four-Bedroom": 1008,
                "FMR Percentile": 40,
                "statename": "Virginia",
                "statecode": "VA",
                "smallarea_status": "0"
            },
            {
                "town_name": null,
                "county_name": "Brunswick County",
                "metro_name": "Brunswick County, VA",
                "fips_code": "5102599999",
                "Efficiency": 499,
                "One-Bedroom": 561,
                "Two-Bedroom": 739,
                "Three-Bedroom": 921,
                "Four-Bedroom": 1031,
                "FMR Percentile": 40,
                "statename": "Virginia",
                "statecode": "VA",
                "smallarea_status": "0"
            },
            {
                "town_name": null,
                "county_name": "Buchanan County",
                "metro_name": "Buchanan County, VA",
                "fips_code": "5102799999",
                "Efficiency": 601,
                "One-Bedroom": 615,
                "Two-Bedroom": 701,
                "Three-Bedroom": 880,
                "Four-Bedroom": 951,
                "FMR Percentile": 40,
                "statename": "Virginia",
                "statecode": "VA",
                "smallarea_status": "0"
            },
            {
                "town_name": null,
                "county_name": "Buckingham County",
                "metro_name": "Buckingham County, VA HUD Metro FMR Area",
                "fips_code": "5102999999",
                "Efficiency": 564,
                "One-Bedroom": 652,
                "Two-Bedroom": 743,
                "Three-Bedroom": 1007,
                "Four-Bedroom": 1140,
                "FMR Percentile": 40,
                "statename": "Virginia",
                "statecode": "VA",
                "smallarea_status": "0"
            },
            {
                "town_name": null,
                "county_name": "Buena Vista city",
                "metro_name": "Rockbridge County-Buena Vista city-Lexington city, VA HUD Nonmetro FMR Area",
                "fips_code": "5153099999",
                "Efficiency": 508,
                "One-Bedroom": 620,
                "Two-Bedroom": 770,
                "Three-Bedroom": 1029,
                "Four-Bedroom": 1049,
                "FMR Percentile": 40,
                "statename": "Virginia",
                "statecode": "VA",
                "smallarea_status": "0"
            },
            {
                "town_name": null,
                "county_name": "Campbell County",
                "metro_name": "Lynchburg, VA MSA",
                "fips_code": "5103199999",
                "Efficiency": 633,
                "One-Bedroom": 660,
                "Two-Bedroom": 784,
                "Three-Bedroom": 1053,
                "Four-Bedroom": 1241,
                "FMR Percentile": 40,
                "statename": "Virginia",
                "statecode": "VA",
                "smallarea_status": "0"
            },
            {
                "town_name": null,
                "county_name": "Caroline County",
                "metro_name": "Richmond, VA MSA",
                "fips_code": "5103399999",
                "Efficiency": 993,
                "One-Bedroom": 1020,
                "Two-Bedroom": 1163,
                "Three-Bedroom": 1538,
                "Four-Bedroom": 1840,
                "FMR Percentile": 40,
                "statename": "Virginia",
                "statecode": "VA",
                "smallarea_status": "0"
            },
            {
                "town_name": null,
                "county_name": "Carroll County",
                "metro_name": "Carroll County-Galax city, VA HUD Nonmetro FMR Area",
                "fips_code": "5103599999",
                "Efficiency": 472,
                "One-Bedroom": 615,
                "Two-Bedroom": 701,
                "Three-Bedroom": 947,
                "Four-Bedroom": 966,
                "FMR Percentile": 40,
                "statename": "Virginia",
                "statecode": "VA",
                "smallarea_status": "0"
            },
            {
                "town_name": null,
                "county_name": "Charles City County",
                "metro_name": "Richmond, VA MSA",
                "fips_code": "5103699999",
                "Efficiency": 993,
                "One-Bedroom": 1020,
                "Two-Bedroom": 1163,
                "Three-Bedroom": 1538,
                "Four-Bedroom": 1840,
                "FMR Percentile": 40,
                "statename": "Virginia",
                "statecode": "VA",
                "smallarea_status": "0"
            },
            {
                "town_name": null,
                "county_name": "Charlotte County",
                "metro_name": "Charlotte County, VA",
                "fips_code": "5103799999",
                "Efficiency": 472,
                "One-Bedroom": 556,
                "Two-Bedroom": 701,
                "Three-Bedroom": 913,
                "Four-Bedroom": 951,
                "FMR Percentile": 40,
                "statename": "Virginia",
                "statecode": "VA",
                "smallarea_status": "0"
            },
            {
                "town_name": null,
                "county_name": "Charlottesville city",
                "metro_name": "Charlottesville, VA HUD Metro FMR Area",
                "fips_code": "5154099999",
                "Efficiency": 949,
                "One-Bedroom": 1077,
                "Two-Bedroom": 1266,
                "Three-Bedroom": 1575,
                "Four-Bedroom": 1965,
                "FMR Percentile": 40,
                "statename": "Virginia",
                "statecode": "VA",
                "smallarea_status": "0"
            },
            {
                "town_name": null,
                "county_name": "Chesapeake city",
                "metro_name": "Virginia Beach-Norfolk-Newport News, VA-NC HUD Metro FMR Area",
                "fips_code": "5155099999",
                "Efficiency": 960,
                "One-Bedroom": 972,
                "Two-Bedroom": 1147,
                "Three-Bedroom": 1618,
                "Four-Bedroom": 1986,
                "FMR Percentile": 40,
                "statename": "Virginia",
                "statecode": "VA",
                "smallarea_status": "0"
            },
            {
                "town_name": null,
                "county_name": "Chesterfield County",
                "metro_name": "Richmond, VA MSA",
                "fips_code": "5104199999",
                "Efficiency": 993,
                "One-Bedroom": 1020,
                "Two-Bedroom": 1163,
                "Three-Bedroom": 1538,
                "Four-Bedroom": 1840,
                "FMR Percentile": 40,
                "statename": "Virginia",
                "statecode": "VA",
                "smallarea_status": "0"
            },
            {
                "town_name": null,
                "county_name": "Clarke County",
                "metro_name": "Washington-Arlington-Alexandria, DC-VA-MD HUD Metro FMR Area",
                "fips_code": "5104399999",
                "Efficiency": 1513,
                "One-Bedroom": 1548,
                "Two-Bedroom": 1765,
                "Three-Bedroom": 2263,
                "Four-Bedroom": 2742,
                "FMR Percentile": 40,
                "statename": "Virginia",
                "statecode": "VA",
                "smallarea_status": "1"
            },
            {
                "town_name": null,
                "county_name": "Colonial Heights city",
                "metro_name": "Richmond, VA MSA",
                "fips_code": "5157099999",
                "Efficiency": 993,
                "One-Bedroom": 1020,
                "Two-Bedroom": 1163,
                "Three-Bedroom": 1538,
                "Four-Bedroom": 1840,
                "FMR Percentile": 40,
                "statename": "Virginia",
                "statecode": "VA",
                "smallarea_status": "0"
            },
            {
                "town_name": null,
                "county_name": "Covington city",
                "metro_name": "Alleghany County-Clifton Forge city-Covington city, VA HUD Nonmetro FMR Area",
                "fips_code": "5158099999",
                "Efficiency": 495,
                "One-Bedroom": 558,
                "Two-Bedroom": 735,
                "Three-Bedroom": 958,
                "Four-Bedroom": 1142,
                "FMR Percentile": 40,
                "statename": "Virginia",
                "statecode": "VA",
                "smallarea_status": "0"
            },
            {
                "town_name": null,
                "county_name": "Craig County",
                "metro_name": "Roanoke, VA HUD Metro FMR Area",
                "fips_code": "5104599999",
                "Efficiency": 641,
                "One-Bedroom": 743,
                "Two-Bedroom": 941,
                "Three-Bedroom": 1268,
                "Four-Bedroom": 1387,
                "FMR Percentile": 40,
                "statename": "Virginia",
                "statecode": "VA",
                "smallarea_status": "0"
            },
            {
                "town_name": null,
                "county_name": "Culpeper County",
                "metro_name": "Culpeper County, VA HUD Metro FMR Area",
                "fips_code": "5104799999",
                "Efficiency": 788,
                "One-Bedroom": 794,
                "Two-Bedroom": 1046,
                "Three-Bedroom": 1439,
                "Four-Bedroom": 1811,
                "FMR Percentile": 40,
                "statename": "Virginia",
                "statecode": "VA",
                "smallarea_status": "0"
            },
            {
                "town_name": null,
                "county_name": "Cumberland County",
                "metro_name": "Cumberland County, VA",
                "fips_code": "5104999999",
                "Efficiency": 626,
                "One-Bedroom": 737,
                "Two-Bedroom": 929,
                "Three-Bedroom": 1156,
                "Four-Bedroom": 1372,
                "FMR Percentile": 40,
                "statename": "Virginia",
                "statecode": "VA",
                "smallarea_status": "0"
            },
            {
                "town_name": null,
                "county_name": "Danville city",
                "metro_name": "Pittsylvania County-Danville city, VA HUD Nonmetro FMR Area",
                "fips_code": "5159099999",
                "Efficiency": 470,
                "One-Bedroom": 532,
                "Two-Bedroom": 701,
                "Three-Bedroom": 926,
                "Four-Bedroom": 1065,
                "FMR Percentile": 40,
                "statename": "Virginia",
                "statecode": "VA",
                "smallarea_status": "0"
            },
            {
                "town_name": null,
                "county_name": "Dickenson County",
                "metro_name": "Dickenson County, VA",
                "fips_code": "5105199999",
                "Efficiency": 472,
                "One-Bedroom": 615,
                "Two-Bedroom": 701,
                "Three-Bedroom": 911,
                "Four-Bedroom": 1138,
                "FMR Percentile": 40,
                "statename": "Virginia",
                "statecode": "VA",
                "smallarea_status": "0"
            },
            {
                "town_name": null,
                "county_name": "Dinwiddie County",
                "metro_name": "Richmond, VA MSA",
                "fips_code": "5105399999",
                "Efficiency": 993,
                "One-Bedroom": 1020,
                "Two-Bedroom": 1163,
                "Three-Bedroom": 1538,
                "Four-Bedroom": 1840,
                "FMR Percentile": 40,
                "statename": "Virginia",
                "statecode": "VA",
                "smallarea_status": "0"
            },
            {
                "town_name": null,
                "county_name": "Emporia city",
                "metro_name": "Greensville County-Emporia city, VA HUD Nonmetro FMR Area",
                "fips_code": "5159599999",
                "Efficiency": 525,
                "One-Bedroom": 592,
                "Two-Bedroom": 780,
                "Three-Bedroom": 1054,
                "Four-Bedroom": 1058,
                "FMR Percentile": 40,
                "statename": "Virginia",
                "statecode": "VA",
                "smallarea_status": "0"
            },
            {
                "town_name": null,
                "county_name": "Essex County",
                "metro_name": "Essex County, VA",
                "fips_code": "5105799999",
                "Efficiency": 603,
                "One-Bedroom": 697,
                "Two-Bedroom": 895,
                "Three-Bedroom": 1113,
                "Four-Bedroom": 1321,
                "FMR Percentile": 40,
                "statename": "Virginia",
                "statecode": "VA",
                "smallarea_status": "0"
            },
            {
                "town_name": null,
                "county_name": "Fairfax city",
                "metro_name": "Washington-Arlington-Alexandria, DC-VA-MD HUD Metro FMR Area",
                "fips_code": "5160099999",
                "Efficiency": 1513,
                "One-Bedroom": 1548,
                "Two-Bedroom": 1765,
                "Three-Bedroom": 2263,
                "Four-Bedroom": 2742,
                "FMR Percentile": 40,
                "statename": "Virginia",
                "statecode": "VA",
                "smallarea_status": "1"
            },
            {
                "town_name": null,
                "county_name": "Fairfax County",
                "metro_name": "Washington-Arlington-Alexandria, DC-VA-MD HUD Metro FMR Area",
                "fips_code": "5105999999",
                "Efficiency": 1513,
                "One-Bedroom": 1548,
                "Two-Bedroom": 1765,
                "Three-Bedroom": 2263,
                "Four-Bedroom": 2742,
                "FMR Percentile": 40,
                "statename": "Virginia",
                "statecode": "VA",
                "smallarea_status": "1"
            },
            {
                "town_name": null,
                "county_name": "Falls Church city",
                "metro_name": "Washington-Arlington-Alexandria, DC-VA-MD HUD Metro FMR Area",
                "fips_code": "5161099999",
                "Efficiency": 1513,
                "One-Bedroom": 1548,
                "Two-Bedroom": 1765,
                "Three-Bedroom": 2263,
                "Four-Bedroom": 2742,
                "FMR Percentile": 40,
                "statename": "Virginia",
                "statecode": "VA",
                "smallarea_status": "1"
            },
            {
                "town_name": null,
                "county_name": "Fauquier County",
                "metro_name": "Washington-Arlington-Alexandria, DC-VA-MD HUD Metro FMR Area",
                "fips_code": "5106199999",
                "Efficiency": 1513,
                "One-Bedroom": 1548,
                "Two-Bedroom": 1765,
                "Three-Bedroom": 2263,
                "Four-Bedroom": 2742,
                "FMR Percentile": 40,
                "statename": "Virginia",
                "statecode": "VA",
                "smallarea_status": "1"
            },
            {
                "town_name": null,
                "county_name": "Floyd County",
                "metro_name": "Floyd County, VA HUD Metro FMR Area",
                "fips_code": "5106399999",
                "Efficiency": 601,
                "One-Bedroom": 615,
                "Two-Bedroom": 701,
                "Three-Bedroom": 1003,
                "Four-Bedroom": 1214,
                "FMR Percentile": 40,
                "statename": "Virginia",
                "statecode": "VA",
                "smallarea_status": "0"
            },
            {
                "town_name": null,
                "county_name": "Fluvanna County",
                "metro_name": "Charlottesville, VA HUD Metro FMR Area",
                "fips_code": "5106599999",
                "Efficiency": 949,
                "One-Bedroom": 1077,
                "Two-Bedroom": 1266,
                "Three-Bedroom": 1575,
                "Four-Bedroom": 1965,
                "FMR Percentile": 40,
                "statename": "Virginia",
                "statecode": "VA",
                "smallarea_status": "0"
            },
            {
                "town_name": null,
                "county_name": "Franklin city",
                "metro_name": "Southampton County-Franklin city, VA HUD Nonmetro FMR Area",
                "fips_code": "5162099999",
                "Efficiency": 563,
                "One-Bedroom": 690,
                "Two-Bedroom": 786,
                "Three-Bedroom": 1096,
                "Four-Bedroom": 1361,
                "FMR Percentile": 40,
                "statename": "Virginia",
                "statecode": "VA",
                "smallarea_status": "0"
            },
            {
                "town_name": null,
                "county_name": "Franklin County",
                "metro_name": "Franklin County, VA HUD Metro FMR Area",
                "fips_code": "5106799999",
                "Efficiency": 575,
                "One-Bedroom": 618,
                "Two-Bedroom": 815,
                "Three-Bedroom": 1014,
                "Four-Bedroom": 1127,
                "FMR Percentile": 40,
                "statename": "Virginia",
                "statecode": "VA",
                "smallarea_status": "0"
            },
            {
                "town_name": null,
                "county_name": "Frederick County",
                "metro_name": "Winchester, VA-WV MSA",
                "fips_code": "5106999999",
                "Efficiency": 814,
                "One-Bedroom": 819,
                "Two-Bedroom": 1064,
                "Three-Bedroom": 1399,
                "Four-Bedroom": 1814,
                "FMR Percentile": 40,
                "statename": "Virginia",
                "statecode": "VA",
                "smallarea_status": "0"
            },
            {
                "town_name": null,
                "county_name": "Fredericksburg city",
                "metro_name": "Washington-Arlington-Alexandria, DC-VA-MD HUD Metro FMR Area",
                "fips_code": "5163099999",
                "Efficiency": 1513,
                "One-Bedroom": 1548,
                "Two-Bedroom": 1765,
                "Three-Bedroom": 2263,
                "Four-Bedroom": 2742,
                "FMR Percentile": 40,
                "statename": "Virginia",
                "statecode": "VA",
                "smallarea_status": "1"
            },
            {
                "town_name": null,
                "county_name": "Galax city",
                "metro_name": "Carroll County-Galax city, VA HUD Nonmetro FMR Area",
                "fips_code": "5164099999",
                "Efficiency": 472,
                "One-Bedroom": 615,
                "Two-Bedroom": 701,
                "Three-Bedroom": 947,
                "Four-Bedroom": 966,
                "FMR Percentile": 40,
                "statename": "Virginia",
                "statecode": "VA",
                "smallarea_status": "0"
            },
            {
                "town_name": null,
                "county_name": "Giles County",
                "metro_name": "Giles County, VA HUD Metro FMR Area",
                "fips_code": "5107199999",
                "Efficiency": 504,
                "One-Bedroom": 655,
                "Two-Bedroom": 747,
                "Three-Bedroom": 982,
                "Four-Bedroom": 1099,
                "FMR Percentile": 40,
                "statename": "Virginia",
                "statecode": "VA",
                "smallarea_status": "0"
            },
            {
                "town_name": null,
                "county_name": "Gloucester County",
                "metro_name": "Virginia Beach-Norfolk-Newport News, VA-NC HUD Metro FMR Area",
                "fips_code": "5107399999",
                "Efficiency": 960,
                "One-Bedroom": 972,
                "Two-Bedroom": 1147,
                "Three-Bedroom": 1618,
                "Four-Bedroom": 1986,
                "FMR Percentile": 40,
                "statename": "Virginia",
                "statecode": "VA",
                "smallarea_status": "0"
            },
            {
                "town_name": null,
                "county_name": "Goochland County",
                "metro_name": "Richmond, VA MSA",
                "fips_code": "5107599999",
                "Efficiency": 993,
                "One-Bedroom": 1020,
                "Two-Bedroom": 1163,
                "Three-Bedroom": 1538,
                "Four-Bedroom": 1840,
                "FMR Percentile": 40,
                "statename": "Virginia",
                "statecode": "VA",
                "smallarea_status": "0"
            },
            {
                "town_name": null,
                "county_name": "Grayson County",
                "metro_name": "Grayson County, VA",
                "fips_code": "5107799999",
                "Efficiency": 472,
                "One-Bedroom": 615,
                "Two-Bedroom": 701,
                "Three-Bedroom": 954,
                "Four-Bedroom": 957,
                "FMR Percentile": 40,
                "statename": "Virginia",
                "statecode": "VA",
                "smallarea_status": "0"
            },
            {
                "town_name": null,
                "county_name": "Greene County",
                "metro_name": "Charlottesville, VA HUD Metro FMR Area",
                "fips_code": "5107999999",
                "Efficiency": 949,
                "One-Bedroom": 1077,
                "Two-Bedroom": 1266,
                "Three-Bedroom": 1575,
                "Four-Bedroom": 1965,
                "FMR Percentile": 40,
                "statename": "Virginia",
                "statecode": "VA",
                "smallarea_status": "0"
            },
            {
                "town_name": null,
                "county_name": "Greensville County",
                "metro_name": "Greensville County-Emporia city, VA HUD Nonmetro FMR Area",
                "fips_code": "5108199999",
                "Efficiency": 525,
                "One-Bedroom": 592,
                "Two-Bedroom": 780,
                "Three-Bedroom": 1054,
                "Four-Bedroom": 1058,
                "FMR Percentile": 40,
                "statename": "Virginia",
                "statecode": "VA",
                "smallarea_status": "0"
            },
            {
                "town_name": null,
                "county_name": "Halifax County",
                "metro_name": "Halifax County, VA",
                "fips_code": "5108399999",
                "Efficiency": 472,
                "One-Bedroom": 532,
                "Two-Bedroom": 701,
                "Three-Bedroom": 901,
                "Four-Bedroom": 951,
                "FMR Percentile": 40,
                "statename": "Virginia",
                "statecode": "VA",
                "smallarea_status": "0"
            },
            {
                "town_name": null,
                "county_name": "Hampton city",
                "metro_name": "Virginia Beach-Norfolk-Newport News, VA-NC HUD Metro FMR Area",
                "fips_code": "5165099999",
                "Efficiency": 960,
                "One-Bedroom": 972,
                "Two-Bedroom": 1147,
                "Three-Bedroom": 1618,
                "Four-Bedroom": 1986,
                "FMR Percentile": 40,
                "statename": "Virginia",
                "statecode": "VA",
                "smallarea_status": "0"
            },
            {
                "town_name": null,
                "county_name": "Hanover County",
                "metro_name": "Richmond, VA MSA",
                "fips_code": "5108599999",
                "Efficiency": 993,
                "One-Bedroom": 1020,
                "Two-Bedroom": 1163,
                "Three-Bedroom": 1538,
                "Four-Bedroom": 1840,
                "FMR Percentile": 40,
                "statename": "Virginia",
                "statecode": "VA",
                "smallarea_status": "0"
            },
            {
                "town_name": null,
                "county_name": "Harrisonburg city",
                "metro_name": "Harrisonburg, VA MSA",
                "fips_code": "5166099999",
                "Efficiency": 699,
                "One-Bedroom": 703,
                "Two-Bedroom": 927,
                "Three-Bedroom": 1207,
                "Four-Bedroom": 1605,
                "FMR Percentile": 40,
                "statename": "Virginia",
                "statecode": "VA",
                "smallarea_status": "0"
            },
            {
                "town_name": null,
                "county_name": "Henrico County",
                "metro_name": "Richmond, VA MSA",
                "fips_code": "5108799999",
                "Efficiency": 993,
                "One-Bedroom": 1020,
                "Two-Bedroom": 1163,
                "Three-Bedroom": 1538,
                "Four-Bedroom": 1840,
                "FMR Percentile": 40,
                "statename": "Virginia",
                "statecode": "VA",
                "smallarea_status": "0"
            },
            {
                "town_name": null,
                "county_name": "Henry County",
                "metro_name": "Henry County-Martinsville city, VA HUD Nonmetro FMR Area",
                "fips_code": "5108999999",
                "Efficiency": 528,
                "One-Bedroom": 532,
                "Two-Bedroom": 701,
                "Three-Bedroom": 915,
                "Four-Bedroom": 1000,
                "FMR Percentile": 40,
                "statename": "Virginia",
                "statecode": "VA",
                "smallarea_status": "0"
            },
            {
                "town_name": null,
                "county_name": "Highland County",
                "metro_name": "Highland County, VA",
                "fips_code": "5109199999",
                "Efficiency": 472,
                "One-Bedroom": 556,
                "Two-Bedroom": 701,
                "Three-Bedroom": 932,
                "Four-Bedroom": 1035,
                "FMR Percentile": 40,
                "statename": "Virginia",
                "statecode": "VA",
                "smallarea_status": "0"
            },
            {
                "town_name": null,
                "county_name": "Hopewell city",
                "metro_name": "Richmond, VA MSA",
                "fips_code": "5167099999",
                "Efficiency": 993,
                "One-Bedroom": 1020,
                "Two-Bedroom": 1163,
                "Three-Bedroom": 1538,
                "Four-Bedroom": 1840,
                "FMR Percentile": 40,
                "statename": "Virginia",
                "statecode": "VA",
                "smallarea_status": "0"
            },
            {
                "town_name": null,
                "county_name": "Isle of Wight County",
                "metro_name": "Virginia Beach-Norfolk-Newport News, VA-NC HUD Metro FMR Area",
                "fips_code": "5109399999",
                "Efficiency": 960,
                "One-Bedroom": 972,
                "Two-Bedroom": 1147,
                "Three-Bedroom": 1618,
                "Four-Bedroom": 1986,
                "FMR Percentile": 40,
                "statename": "Virginia",
                "statecode": "VA",
                "smallarea_status": "0"
            },
            {
                "town_name": null,
                "county_name": "James City County",
                "metro_name": "Virginia Beach-Norfolk-Newport News, VA-NC HUD Metro FMR Area",
                "fips_code": "5109599999",
                "Efficiency": 960,
                "One-Bedroom": 972,
                "Two-Bedroom": 1147,
                "Three-Bedroom": 1618,
                "Four-Bedroom": 1986,
                "FMR Percentile": 40,
                "statename": "Virginia",
                "statecode": "VA",
                "smallarea_status": "0"
            },
            {
                "town_name": null,
                "county_name": "King and Queen County",
                "metro_name": "King and Queen County, VA",
                "fips_code": "5109799999",
                "Efficiency": 538,
                "One-Bedroom": 635,
                "Two-Bedroom": 797,
                "Three-Bedroom": 1068,
                "Four-Bedroom": 1197,
                "FMR Percentile": 40,
                "statename": "Virginia",
                "statecode": "VA",
                "smallarea_status": "0"
            },
            {
                "town_name": null,
                "county_name": "King George County",
                "metro_name": "King George County, VA",
                "fips_code": "5109999999",
                "Efficiency": 723,
                "One-Bedroom": 846,
                "Two-Bedroom": 1073,
                "Three-Bedroom": 1536,
                "Four-Bedroom": 1584,
                "FMR Percentile": 40,
                "statename": "Virginia",
                "statecode": "VA",
                "smallarea_status": "0"
            },
            {
                "town_name": null,
                "county_name": "King William County",
                "metro_name": "Richmond, VA MSA",
                "fips_code": "5110199999",
                "Efficiency": 993,
                "One-Bedroom": 1020,
                "Two-Bedroom": 1163,
                "Three-Bedroom": 1538,
                "Four-Bedroom": 1840,
                "FMR Percentile": 40,
                "statename": "Virginia",
                "statecode": "VA",
                "smallarea_status": "0"
            },
            {
                "town_name": null,
                "county_name": "Lancaster County",
                "metro_name": "Lancaster County, VA",
                "fips_code": "5110399999",
                "Efficiency": 640,
                "One-Bedroom": 753,
                "Two-Bedroom": 950,
                "Three-Bedroom": 1182,
                "Four-Bedroom": 1288,
                "FMR Percentile": 40,
                "statename": "Virginia",
                "statecode": "VA",
                "smallarea_status": "0"
            },
            {
                "town_name": null,
                "county_name": "Lee County",
                "metro_name": "Lee County, VA",
                "fips_code": "5110599999",
                "Efficiency": 472,
                "One-Bedroom": 599,
                "Two-Bedroom": 701,
                "Three-Bedroom": 899,
                "Four-Bedroom": 1013,
                "FMR Percentile": 40,
                "statename": "Virginia",
                "statecode": "VA",
                "smallarea_status": "0"
            },
            {
                "town_name": null,
                "county_name": "Lexington city",
                "metro_name": "Rockbridge County-Buena Vista city-Lexington city, VA HUD Nonmetro FMR Area",
                "fips_code": "5167899999",
                "Efficiency": 508,
                "One-Bedroom": 620,
                "Two-Bedroom": 770,
                "Three-Bedroom": 1029,
                "Four-Bedroom": 1049,
                "FMR Percentile": 40,
                "statename": "Virginia",
                "statecode": "VA",
                "smallarea_status": "0"
            },
            {
                "town_name": null,
                "county_name": "Loudoun County",
                "metro_name": "Washington-Arlington-Alexandria, DC-VA-MD HUD Metro FMR Area",
                "fips_code": "5110799999",
                "Efficiency": 1513,
                "One-Bedroom": 1548,
                "Two-Bedroom": 1765,
                "Three-Bedroom": 2263,
                "Four-Bedroom": 2742,
                "FMR Percentile": 40,
                "statename": "Virginia",
                "statecode": "VA",
                "smallarea_status": "1"
            },
            {
                "town_name": null,
                "county_name": "Louisa County",
                "metro_name": "Louisa County, VA",
                "fips_code": "5110999999",
                "Efficiency": 613,
                "One-Bedroom": 799,
                "Two-Bedroom": 911,
                "Three-Bedroom": 1238,
                "Four-Bedroom": 1577,
                "FMR Percentile": 40,
                "statename": "Virginia",
                "statecode": "VA",
                "smallarea_status": "0"
            },
            {
                "town_name": null,
                "county_name": "Lunenburg County",
                "metro_name": "Lunenburg County, VA",
                "fips_code": "5111199999",
                "Efficiency": 472,
                "One-Bedroom": 615,
                "Two-Bedroom": 701,
                "Three-Bedroom": 970,
                "Four-Bedroom": 1214,
                "FMR Percentile": 40,
                "statename": "Virginia",
                "statecode": "VA",
                "smallarea_status": "0"
            },
            {
                "town_name": null,
                "county_name": "Lynchburg city",
                "metro_name": "Lynchburg, VA MSA",
                "fips_code": "5168099999",
                "Efficiency": 633,
                "One-Bedroom": 660,
                "Two-Bedroom": 784,
                "Three-Bedroom": 1053,
                "Four-Bedroom": 1241,
                "FMR Percentile": 40,
                "statename": "Virginia",
                "statecode": "VA",
                "smallarea_status": "0"
            },
            {
                "town_name": null,
                "county_name": "Madison County",
                "metro_name": "Madison County, VA",
                "fips_code": "5111399999",
                "Efficiency": 621,
                "One-Bedroom": 700,
                "Two-Bedroom": 922,
                "Three-Bedroom": 1147,
                "Four-Bedroom": 1361,
                "FMR Percentile": 40,
                "statename": "Virginia",
                "statecode": "VA",
                "smallarea_status": "0"
            },
            {
                "town_name": null,
                "county_name": "Manassas city",
                "metro_name": "Washington-Arlington-Alexandria, DC-VA-MD HUD Metro FMR Area",
                "fips_code": "5168399999",
                "Efficiency": 1513,
                "One-Bedroom": 1548,
                "Two-Bedroom": 1765,
                "Three-Bedroom": 2263,
                "Four-Bedroom": 2742,
                "FMR Percentile": 40,
                "statename": "Virginia",
                "statecode": "VA",
                "smallarea_status": "1"
            },
            {
                "town_name": null,
                "county_name": "Manassas Park city",
                "metro_name": "Washington-Arlington-Alexandria, DC-VA-MD HUD Metro FMR Area",
                "fips_code": "5168599999",
                "Efficiency": 1513,
                "One-Bedroom": 1548,
                "Two-Bedroom": 1765,
                "Three-Bedroom": 2263,
                "Four-Bedroom": 2742,
                "FMR Percentile": 40,
                "statename": "Virginia",
                "statecode": "VA",
                "smallarea_status": "1"
            },
            {
                "town_name": null,
                "county_name": "Martinsville city",
                "metro_name": "Henry County-Martinsville city, VA HUD Nonmetro FMR Area",
                "fips_code": "5169099999",
                "Efficiency": 528,
                "One-Bedroom": 532,
                "Two-Bedroom": 701,
                "Three-Bedroom": 915,
                "Four-Bedroom": 1000,
                "FMR Percentile": 40,
                "statename": "Virginia",
                "statecode": "VA",
                "smallarea_status": "0"
            },
            {
                "town_name": null,
                "county_name": "Mathews County",
                "metro_name": "Virginia Beach-Norfolk-Newport News, VA-NC HUD Metro FMR Area",
                "fips_code": "5111599999",
                "Efficiency": 960,
                "One-Bedroom": 972,
                "Two-Bedroom": 1147,
                "Three-Bedroom": 1618,
                "Four-Bedroom": 1986,
                "FMR Percentile": 40,
                "statename": "Virginia",
                "statecode": "VA",
                "smallarea_status": "0"
            },
            {
                "town_name": null,
                "county_name": "Mecklenburg County",
                "metro_name": "Mecklenburg County, VA",
                "fips_code": "5111799999",
                "Efficiency": 485,
                "One-Bedroom": 632,
                "Two-Bedroom": 720,
                "Three-Bedroom": 958,
                "Four-Bedroom": 1083,
                "FMR Percentile": 40,
                "statename": "Virginia",
                "statecode": "VA",
                "smallarea_status": "0"
            },
            {
                "town_name": null,
                "county_name": "Middlesex County",
                "metro_name": "Middlesex County, VA",
                "fips_code": "5111999999",
                "Efficiency": 617,
                "One-Bedroom": 727,
                "Two-Bedroom": 917,
                "Three-Bedroom": 1141,
                "Four-Bedroom": 1354,
                "FMR Percentile": 40,
                "statename": "Virginia",
                "statecode": "VA",
                "smallarea_status": "0"
            },
            {
                "town_name": null,
                "county_name": "Montgomery County",
                "metro_name": "Blacksburg-Christiansburg-Radford, VA HUD Metro FMR Area",
                "fips_code": "5112199999",
                "Efficiency": 795,
                "One-Bedroom": 858,
                "Two-Bedroom": 978,
                "Three-Bedroom": 1400,
                "Four-Bedroom": 1693,
                "FMR Percentile": 40,
                "statename": "Virginia",
                "statecode": "VA",
                "smallarea_status": "0"
            },
            {
                "town_name": null,
                "county_name": "Nelson County",
                "metro_name": "Charlottesville, VA HUD Metro FMR Area",
                "fips_code": "5112599999",
                "Efficiency": 949,
                "One-Bedroom": 1077,
                "Two-Bedroom": 1266,
                "Three-Bedroom": 1575,
                "Four-Bedroom": 1965,
                "FMR Percentile": 40,
                "statename": "Virginia",
                "statecode": "VA",
                "smallarea_status": "0"
            },
            {
                "town_name": null,
                "county_name": "New Kent County",
                "metro_name": "Richmond, VA MSA",
                "fips_code": "5112799999",
                "Efficiency": 993,
                "One-Bedroom": 1020,
                "Two-Bedroom": 1163,
                "Three-Bedroom": 1538,
                "Four-Bedroom": 1840,
                "FMR Percentile": 40,
                "statename": "Virginia",
                "statecode": "VA",
                "smallarea_status": "0"
            },
            {
                "town_name": null,
                "county_name": "Newport News city",
                "metro_name": "Virginia Beach-Norfolk-Newport News, VA-NC HUD Metro FMR Area",
                "fips_code": "5170099999",
                "Efficiency": 960,
                "One-Bedroom": 972,
                "Two-Bedroom": 1147,
                "Three-Bedroom": 1618,
                "Four-Bedroom": 1986,
                "FMR Percentile": 40,
                "statename": "Virginia",
                "statecode": "VA",
                "smallarea_status": "0"
            },
            {
                "town_name": null,
                "county_name": "Norfolk city",
                "metro_name": "Virginia Beach-Norfolk-Newport News, VA-NC HUD Metro FMR Area",
                "fips_code": "5171099999",
                "Efficiency": 960,
                "One-Bedroom": 972,
                "Two-Bedroom": 1147,
                "Three-Bedroom": 1618,
                "Four-Bedroom": 1986,
                "FMR Percentile": 40,
                "statename": "Virginia",
                "statecode": "VA",
                "smallarea_status": "0"
            },
            {
                "town_name": null,
                "county_name": "Northampton County",
                "metro_name": "Northampton County, VA",
                "fips_code": "5113199999",
                "Efficiency": 541,
                "One-Bedroom": 704,
                "Two-Bedroom": 803,
                "Three-Bedroom": 1098,
                "Four-Bedroom": 1118,
                "FMR Percentile": 40,
                "statename": "Virginia",
                "statecode": "VA",
                "smallarea_status": "0"
            },
            {
                "town_name": null,
                "county_name": "Northumberland County",
                "metro_name": "Northumberland County, VA",
                "fips_code": "5113399999",
                "Efficiency": 534,
                "One-Bedroom": 629,
                "Two-Bedroom": 793,
                "Three-Bedroom": 1135,
                "Four-Bedroom": 1171,
                "FMR Percentile": 40,
                "statename": "Virginia",
                "statecode": "VA",
                "smallarea_status": "0"
            },
            {
                "town_name": null,
                "county_name": "Norton city",
                "metro_name": "Wise County-Norton city, VA HUD Nonmetro FMR Area",
                "fips_code": "5172099999",
                "Efficiency": 472,
                "One-Bedroom": 532,
                "Two-Bedroom": 701,
                "Three-Bedroom": 912,
                "Four-Bedroom": 951,
                "FMR Percentile": 40,
                "statename": "Virginia",
                "statecode": "VA",
                "smallarea_status": "0"
            },
            {
                "town_name": null,
                "county_name": "Nottoway County",
                "metro_name": "Nottoway County, VA",
                "fips_code": "5113599999",
                "Efficiency": 510,
                "One-Bedroom": 664,
                "Two-Bedroom": 757,
                "Three-Bedroom": 1051,
                "Four-Bedroom": 1231,
                "FMR Percentile": 40,
                "statename": "Virginia",
                "statecode": "VA",
                "smallarea_status": "0"
            },
            {
                "town_name": null,
                "county_name": "Orange County",
                "metro_name": "Orange County, VA",
                "fips_code": "5113799999",
                "Efficiency": 720,
                "One-Bedroom": 725,
                "Two-Bedroom": 903,
                "Three-Bedroom": 1261,
                "Four-Bedroom": 1377,
                "FMR Percentile": 40,
                "statename": "Virginia",
                "statecode": "VA",
                "smallarea_status": "0"
            },
            {
                "town_name": null,
                "county_name": "Page County",
                "metro_name": "Page County, VA",
                "fips_code": "5113999999",
                "Efficiency": 493,
                "One-Bedroom": 604,
                "Two-Bedroom": 732,
                "Three-Bedroom": 938,
                "Four-Bedroom": 1184,
                "FMR Percentile": 40,
                "statename": "Virginia",
                "statecode": "VA",
                "smallarea_status": "0"
            },
            {
                "town_name": null,
                "county_name": "Patrick County",
                "metro_name": "Patrick County, VA",
                "fips_code": "5114199999",
                "Efficiency": 472,
                "One-Bedroom": 615,
                "Two-Bedroom": 701,
                "Three-Bedroom": 923,
                "Four-Bedroom": 1097,
                "FMR Percentile": 40,
                "statename": "Virginia",
                "statecode": "VA",
                "smallarea_status": "0"
            },
            {
                "town_name": null,
                "county_name": "Petersburg city",
                "metro_name": "Richmond, VA MSA",
                "fips_code": "5173099999",
                "Efficiency": 993,
                "One-Bedroom": 1020,
                "Two-Bedroom": 1163,
                "Three-Bedroom": 1538,
                "Four-Bedroom": 1840,
                "FMR Percentile": 40,
                "statename": "Virginia",
                "statecode": "VA",
                "smallarea_status": "0"
            },
            {
                "town_name": null,
                "county_name": "Pittsylvania County",
                "metro_name": "Pittsylvania County-Danville city, VA HUD Nonmetro FMR Area",
                "fips_code": "5114399999",
                "Efficiency": 470,
                "One-Bedroom": 532,
                "Two-Bedroom": 701,
                "Three-Bedroom": 926,
                "Four-Bedroom": 1065,
                "FMR Percentile": 40,
                "statename": "Virginia",
                "statecode": "VA",
                "smallarea_status": "0"
            },
            {
                "town_name": null,
                "county_name": "Poquoson city",
                "metro_name": "Virginia Beach-Norfolk-Newport News, VA-NC HUD Metro FMR Area",
                "fips_code": "5173599999",
                "Efficiency": 960,
                "One-Bedroom": 972,
                "Two-Bedroom": 1147,
                "Three-Bedroom": 1618,
                "Four-Bedroom": 1986,
                "FMR Percentile": 40,
                "statename": "Virginia",
                "statecode": "VA",
                "smallarea_status": "0"
            },
            {
                "town_name": null,
                "county_name": "Portsmouth city",
                "metro_name": "Virginia Beach-Norfolk-Newport News, VA-NC HUD Metro FMR Area",
                "fips_code": "5174099999",
                "Efficiency": 960,
                "One-Bedroom": 972,
                "Two-Bedroom": 1147,
                "Three-Bedroom": 1618,
                "Four-Bedroom": 1986,
                "FMR Percentile": 40,
                "statename": "Virginia",
                "statecode": "VA",
                "smallarea_status": "0"
            },
            {
                "town_name": null,
                "county_name": "Powhatan County",
                "metro_name": "Richmond, VA MSA",
                "fips_code": "5114599999",
                "Efficiency": 993,
                "One-Bedroom": 1020,
                "Two-Bedroom": 1163,
                "Three-Bedroom": 1538,
                "Four-Bedroom": 1840,
                "FMR Percentile": 40,
                "statename": "Virginia",
                "statecode": "VA",
                "smallarea_status": "0"
            },
            {
                "town_name": null,
                "county_name": "Prince Edward County",
                "metro_name": "Prince Edward County, VA",
                "fips_code": "5114799999",
                "Efficiency": 593,
                "One-Bedroom": 668,
                "Two-Bedroom": 881,
                "Three-Bedroom": 1096,
                "Four-Bedroom": 1301,
                "FMR Percentile": 40,
                "statename": "Virginia",
                "statecode": "VA",
                "smallarea_status": "0"
            },
            {
                "town_name": null,
                "county_name": "Prince George County",
                "metro_name": "Richmond, VA MSA",
                "fips_code": "5114999999",
                "Efficiency": 993,
                "One-Bedroom": 1020,
                "Two-Bedroom": 1163,
                "Three-Bedroom": 1538,
                "Four-Bedroom": 1840,
                "FMR Percentile": 40,
                "statename": "Virginia",
                "statecode": "VA",
                "smallarea_status": "0"
            },
            {
                "town_name": null,
                "county_name": "Prince William County",
                "metro_name": "Washington-Arlington-Alexandria, DC-VA-MD HUD Metro FMR Area",
                "fips_code": "5115399999",
                "Efficiency": 1513,
                "One-Bedroom": 1548,
                "Two-Bedroom": 1765,
                "Three-Bedroom": 2263,
                "Four-Bedroom": 2742,
                "FMR Percentile": 40,
                "statename": "Virginia",
                "statecode": "VA",
                "smallarea_status": "1"
            },
            {
                "town_name": null,
                "county_name": "Pulaski County",
                "metro_name": "Pulaski County, VA HUD Metro FMR Area",
                "fips_code": "5115599999",
                "Efficiency": 618,
                "One-Bedroom": 631,
                "Two-Bedroom": 721,
                "Three-Bedroom": 1005,
                "Four-Bedroom": 1191,
                "FMR Percentile": 40,
                "statename": "Virginia",
                "statecode": "VA",
                "smallarea_status": "0"
            },
            {
                "town_name": null,
                "county_name": "Radford city",
                "metro_name": "Blacksburg-Christiansburg-Radford, VA HUD Metro FMR Area",
                "fips_code": "5175099999",
                "Efficiency": 795,
                "One-Bedroom": 858,
                "Two-Bedroom": 978,
                "Three-Bedroom": 1400,
                "Four-Bedroom": 1693,
                "FMR Percentile": 40,
                "statename": "Virginia",
                "statecode": "VA",
                "smallarea_status": "0"
            },
            {
                "town_name": null,
                "county_name": "Rappahannock County",
                "metro_name": "Rappahannock County, VA HUD Metro FMR Area",
                "fips_code": "5115799999",
                "Efficiency": 921,
                "One-Bedroom": 942,
                "Two-Bedroom": 1074,
                "Three-Bedroom": 1433,
                "Four-Bedroom": 1664,
                "FMR Percentile": 40,
                "statename": "Virginia",
                "statecode": "VA",
                "smallarea_status": "0"
            },
            {
                "town_name": null,
                "county_name": "Richmond city",
                "metro_name": "Richmond, VA MSA",
                "fips_code": "5176099999",
                "Efficiency": 993,
                "One-Bedroom": 1020,
                "Two-Bedroom": 1163,
                "Three-Bedroom": 1538,
                "Four-Bedroom": 1840,
                "FMR Percentile": 40,
                "statename": "Virginia",
                "statecode": "VA",
                "smallarea_status": "0"
            },
            {
                "town_name": null,
                "county_name": "Richmond County",
                "metro_name": "Richmond County, VA",
                "fips_code": "5115999999",
                "Efficiency": 580,
                "One-Bedroom": 653,
                "Two-Bedroom": 861,
                "Three-Bedroom": 1081,
                "Four-Bedroom": 1271,
                "FMR Percentile": 40,
                "statename": "Virginia",
                "statecode": "VA",
                "smallarea_status": "0"
            },
            {
                "town_name": null,
                "county_name": "Roanoke city",
                "metro_name": "Roanoke, VA HUD Metro FMR Area",
                "fips_code": "5177099999",
                "Efficiency": 641,
                "One-Bedroom": 743,
                "Two-Bedroom": 941,
                "Three-Bedroom": 1268,
                "Four-Bedroom": 1387,
                "FMR Percentile": 40,
                "statename": "Virginia",
                "statecode": "VA",
                "smallarea_status": "0"
            },
            {
                "town_name": null,
                "county_name": "Roanoke County",
                "metro_name": "Roanoke, VA HUD Metro FMR Area",
                "fips_code": "5116199999",
                "Efficiency": 641,
                "One-Bedroom": 743,
                "Two-Bedroom": 941,
                "Three-Bedroom": 1268,
                "Four-Bedroom": 1387,
                "FMR Percentile": 40,
                "statename": "Virginia",
                "statecode": "VA",
                "smallarea_status": "0"
            },
            {
                "town_name": null,
                "county_name": "Rockbridge County",
                "metro_name": "Rockbridge County-Buena Vista city-Lexington city, VA HUD Nonmetro FMR Area",
                "fips_code": "5116399999",
                "Efficiency": 508,
                "One-Bedroom": 620,
                "Two-Bedroom": 770,
                "Three-Bedroom": 1029,
                "Four-Bedroom": 1049,
                "FMR Percentile": 40,
                "statename": "Virginia",
                "statecode": "VA",
                "smallarea_status": "0"
            },
            {
                "town_name": null,
                "county_name": "Rockingham County",
                "metro_name": "Harrisonburg, VA MSA",
                "fips_code": "5116599999",
                "Efficiency": 699,
                "One-Bedroom": 703,
                "Two-Bedroom": 927,
                "Three-Bedroom": 1207,
                "Four-Bedroom": 1605,
                "FMR Percentile": 40,
                "statename": "Virginia",
                "statecode": "VA",
                "smallarea_status": "0"
            },
            {
                "town_name": null,
                "county_name": "Russell County",
                "metro_name": "Russell County, VA",
                "fips_code": "5116799999",
                "Efficiency": 472,
                "One-Bedroom": 532,
                "Two-Bedroom": 701,
                "Three-Bedroom": 872,
                "Four-Bedroom": 951,
                "FMR Percentile": 40,
                "statename": "Virginia",
                "statecode": "VA",
                "smallarea_status": "0"
            },
            {
                "town_name": null,
                "county_name": "Salem city",
                "metro_name": "Roanoke, VA HUD Metro FMR Area",
                "fips_code": "5177599999",
                "Efficiency": 641,
                "One-Bedroom": 743,
                "Two-Bedroom": 941,
                "Three-Bedroom": 1268,
                "Four-Bedroom": 1387,
                "FMR Percentile": 40,
                "statename": "Virginia",
                "statecode": "VA",
                "smallarea_status": "0"
            },
            {
                "town_name": null,
                "county_name": "Scott County",
                "metro_name": "Kingsport-Bristol-Bristol, TN-VA MSA",
                "fips_code": "5116999999",
                "Efficiency": 513,
                "One-Bedroom": 533,
                "Two-Bedroom": 701,
                "Three-Bedroom": 916,
                "Four-Bedroom": 1008,
                "FMR Percentile": 40,
                "statename": "Virginia",
                "statecode": "VA",
                "smallarea_status": "0"
            },
            {
                "town_name": null,
                "county_name": "Shenandoah County",
                "metro_name": "Shenandoah County, VA",
                "fips_code": "5117199999",
                "Efficiency": 544,
                "One-Bedroom": 629,
                "Two-Bedroom": 824,
                "Three-Bedroom": 1179,
                "Four-Bedroom": 1346,
                "FMR Percentile": 40,
                "statename": "Virginia",
                "statecode": "VA",
                "smallarea_status": "0"
            },
            {
                "town_name": null,
                "county_name": "Smyth County",
                "metro_name": "Smyth County, VA",
                "fips_code": "5117399999",
                "Efficiency": 472,
                "One-Bedroom": 562,
                "Two-Bedroom": 701,
                "Three-Bedroom": 896,
                "Four-Bedroom": 1113,
                "FMR Percentile": 40,
                "statename": "Virginia",
                "statecode": "VA",
                "smallarea_status": "0"
            },
            {
                "town_name": null,
                "county_name": "Southampton County",
                "metro_name": "Southampton County-Franklin city, VA HUD Nonmetro FMR Area",
                "fips_code": "5117599999",
                "Efficiency": 563,
                "One-Bedroom": 690,
                "Two-Bedroom": 786,
                "Three-Bedroom": 1096,
                "Four-Bedroom": 1361,
                "FMR Percentile": 40,
                "statename": "Virginia",
                "statecode": "VA",
                "smallarea_status": "0"
            },
            {
                "town_name": null,
                "county_name": "Spotsylvania County",
                "metro_name": "Washington-Arlington-Alexandria, DC-VA-MD HUD Metro FMR Area",
                "fips_code": "5117799999",
                "Efficiency": 1513,
                "One-Bedroom": 1548,
                "Two-Bedroom": 1765,
                "Three-Bedroom": 2263,
                "Four-Bedroom": 2742,
                "FMR Percentile": 40,
                "statename": "Virginia",
                "statecode": "VA",
                "smallarea_status": "1"
            },
            {
                "town_name": null,
                "county_name": "Stafford County",
                "metro_name": "Washington-Arlington-Alexandria, DC-VA-MD HUD Metro FMR Area",
                "fips_code": "5117999999",
                "Efficiency": 1513,
                "One-Bedroom": 1548,
                "Two-Bedroom": 1765,
                "Three-Bedroom": 2263,
                "Four-Bedroom": 2742,
                "FMR Percentile": 40,
                "statename": "Virginia",
                "statecode": "VA",
                "smallarea_status": "1"
            },
            {
                "town_name": null,
                "county_name": "Staunton city",
                "metro_name": "Staunton-Waynesboro, VA MSA",
                "fips_code": "5179099999",
                "Efficiency": 690,
                "One-Bedroom": 695,
                "Two-Bedroom": 910,
                "Three-Bedroom": 1239,
                "Four-Bedroom": 1416,
                "FMR Percentile": 40,
                "statename": "Virginia",
                "statecode": "VA",
                "smallarea_status": "0"
            },
            {
                "town_name": null,
                "county_name": "Suffolk city",
                "metro_name": "Virginia Beach-Norfolk-Newport News, VA-NC HUD Metro FMR Area",
                "fips_code": "5180099999",
                "Efficiency": 960,
                "One-Bedroom": 972,
                "Two-Bedroom": 1147,
                "Three-Bedroom": 1618,
                "Four-Bedroom": 1986,
                "FMR Percentile": 40,
                "statename": "Virginia",
                "statecode": "VA",
                "smallarea_status": "0"
            },
            {
                "town_name": null,
                "county_name": "Surry County",
                "metro_name": "Surry County, VA",
                "fips_code": "5118199999",
                "Efficiency": 483,
                "One-Bedroom": 569,
                "Two-Bedroom": 717,
                "Three-Bedroom": 1026,
                "Four-Bedroom": 1241,
                "FMR Percentile": 40,
                "statename": "Virginia",
                "statecode": "VA",
                "smallarea_status": "0"
            },
            {
                "town_name": null,
                "county_name": "Sussex County",
                "metro_name": "Richmond, VA MSA",
                "fips_code": "5118399999",
                "Efficiency": 993,
                "One-Bedroom": 1020,
                "Two-Bedroom": 1163,
                "Three-Bedroom": 1538,
                "Four-Bedroom": 1840,
                "FMR Percentile": 40,
                "statename": "Virginia",
                "statecode": "VA",
                "smallarea_status": "0"
            },
            {
                "town_name": null,
                "county_name": "Tazewell County",
                "metro_name": "Tazewell County, VA",
                "fips_code": "5118599999",
                "Efficiency": 472,
                "One-Bedroom": 558,
                "Two-Bedroom": 701,
                "Three-Bedroom": 872,
                "Four-Bedroom": 1160,
                "FMR Percentile": 40,
                "statename": "Virginia",
                "statecode": "VA",
                "smallarea_status": "0"
            },
            {
                "town_name": null,
                "county_name": "Virginia Beach city",
                "metro_name": "Virginia Beach-Norfolk-Newport News, VA-NC HUD Metro FMR Area",
                "fips_code": "5181099999",
                "Efficiency": 960,
                "One-Bedroom": 972,
                "Two-Bedroom": 1147,
                "Three-Bedroom": 1618,
                "Four-Bedroom": 1986,
                "FMR Percentile": 40,
                "statename": "Virginia",
                "statecode": "VA",
                "smallarea_status": "0"
            },
            {
                "town_name": null,
                "county_name": "Warren County",
                "metro_name": "Warren County, VA HUD Metro FMR Area",
                "fips_code": "5118799999",
                "Efficiency": 676,
                "One-Bedroom": 777,
                "Two-Bedroom": 1024,
                "Three-Bedroom": 1376,
                "Four-Bedroom": 1773,
                "FMR Percentile": 40,
                "statename": "Virginia",
                "statecode": "VA",
                "smallarea_status": "0"
            },
            {
                "town_name": null,
                "county_name": "Washington County",
                "metro_name": "Kingsport-Bristol-Bristol, TN-VA MSA",
                "fips_code": "5119199999",
                "Efficiency": 513,
                "One-Bedroom": 533,
                "Two-Bedroom": 701,
                "Three-Bedroom": 916,
                "Four-Bedroom": 1008,
                "FMR Percentile": 40,
                "statename": "Virginia",
                "statecode": "VA",
                "smallarea_status": "0"
            },
            {
                "town_name": null,
                "county_name": "Waynesboro city",
                "metro_name": "Staunton-Waynesboro, VA MSA",
                "fips_code": "5182099999",
                "Efficiency": 690,
                "One-Bedroom": 695,
                "Two-Bedroom": 910,
                "Three-Bedroom": 1239,
                "Four-Bedroom": 1416,
                "FMR Percentile": 40,
                "statename": "Virginia",
                "statecode": "VA",
                "smallarea_status": "0"
            },
            {
                "town_name": null,
                "county_name": "Westmoreland County",
                "metro_name": "Westmoreland County, VA",
                "fips_code": "5119399999",
                "Efficiency": 589,
                "One-Bedroom": 663,
                "Two-Bedroom": 874,
                "Three-Bedroom": 1251,
                "Four-Bedroom": 1513,
                "FMR Percentile": 40,
                "statename": "Virginia",
                "statecode": "VA",
                "smallarea_status": "0"
            },
            {
                "town_name": null,
                "county_name": "Williamsburg city",
                "metro_name": "Virginia Beach-Norfolk-Newport News, VA-NC HUD Metro FMR Area",
                "fips_code": "5183099999",
                "Efficiency": 960,
                "One-Bedroom": 972,
                "Two-Bedroom": 1147,
                "Three-Bedroom": 1618,
                "Four-Bedroom": 1986,
                "FMR Percentile": 40,
                "statename": "Virginia",
                "statecode": "VA",
                "smallarea_status": "0"
            },
            {
                "town_name": null,
                "county_name": "Winchester city",
                "metro_name": "Winchester, VA-WV MSA",
                "fips_code": "5184099999",
                "Efficiency": 814,
                "One-Bedroom": 819,
                "Two-Bedroom": 1064,
                "Three-Bedroom": 1399,
                "Four-Bedroom": 1814,
                "FMR Percentile": 40,
                "statename": "Virginia",
                "statecode": "VA",
                "smallarea_status": "0"
            },
            {
                "town_name": null,
                "county_name": "Wise County",
                "metro_name": "Wise County-Norton city, VA HUD Nonmetro FMR Area",
                "fips_code": "5119599999",
                "Efficiency": 472,
                "One-Bedroom": 532,
                "Two-Bedroom": 701,
                "Three-Bedroom": 912,
                "Four-Bedroom": 951,
                "FMR Percentile": 40,
                "statename": "Virginia",
                "statecode": "VA",
                "smallarea_status": "0"
            },
            {
                "town_name": null,
                "county_name": "Wythe County",
                "metro_name": "Wythe County, VA",
                "fips_code": "5119799999",
                "Efficiency": 472,
                "One-Bedroom": 546,
                "Two-Bedroom": 701,
                "Three-Bedroom": 872,
                "Four-Bedroom": 1083,
                "FMR Percentile": 40,
                "statename": "Virginia",
                "statecode": "VA",
                "smallarea_status": "0"
            },
            {
                "town_name": null,
                "county_name": "York County",
                "metro_name": "Virginia Beach-Norfolk-Newport News, VA-NC HUD Metro FMR Area",
                "fips_code": "5119999999",
                "Efficiency": 960,
                "One-Bedroom": 972,
                "Two-Bedroom": 1147,
                "Three-Bedroom": 1618,
                "Four-Bedroom": 1986,
                "FMR Percentile": 40,
                "statename": "Virginia",
                "statecode": "VA",
                "smallarea_status": "0"
            }
        ]
    }
}
